kurumii/__init__.py
kurumii/print_addons.py
krumii-0.2.dist-info/METADATA
krumii-0.2.dist-info/WHEEL
krumii-0.2.dist-info/top_level.txt
krumii-0.2.dist-info/RECORD
