Metadata-Version: 2.1
Name: krumii
Version: 0.2
Summary: Handy tools for Python
Home-page: UNKNOWN
Author: kurumii
License: UNKNOWN
Platform: UNKNOWN
Classifier: Programming Language :: Python :: 3
Classifier: License :: OSI Approved :: MIT License
Classifier: Operating System :: OS Independent
